{
  "success": true,
  "data": {
    "teams": [
      {
        "rosterId": 1,
        "teamName": "208 Ferrari Way",
        "realName": "Landry",
        "sleeperUsername": "lndahayo",
        "nickname": "Landry",
        "tradeCount": 0,
        "winRate": 0,
        "avgMargin": 0,
        "totalValueGained": 0
      },
      {
        "rosterId": 2,
        "teamName": "ProtectFromMayhemLikeMe",
        "realName": "Grant",
        "sleeperUsername": "gnewman4",
        "nickname": "Grant",
        "tradeCount": 0,
        "winRate": 0,
        "avgMargin": 0,
        "totalValueGained": 0
      },
      {
        "rosterId": 3,
        "teamName": "Tyler's (Scared) Titties",
        "realName": "Brevin",
        "sleeperUsername": "brevinowens",
        "nickname": "Brevin",
        "tradeCount": 0,
        "winRate": 0,
        "avgMargin": 0,
        "totalValueGained": 0
      },
      {
        "rosterId": 4,
        "teamName": "Spirit Halloween",
        "realName": "Kyle",
        "sleeperUsername": "thekylecasey",
        "nickname": "Kyle",
        "tradeCount": 0,
        "winRate": 0,
        "avgMargin": 0,
        "totalValueGained": 0
      },
      {
        "rosterId": 5,
        "teamName": "Mommy Rainier",
        "realName": "Zach",
        "sleeperUsername": "zachlearningtogolf",
        "nickname": "Zach",
        "tradeCount": 0,
        "winRate": 0,
        "avgMargin": 0,
        "totalValueGained": 0
      },
      {
        "rosterId": 6,
        "teamName": "Washed",
        "realName": "Chris",
        "sleeperUsername": "cjsyregelas",
        "nickname": "Chris",
        "tradeCount": 0,
        "winRate": 0,
        "avgMargin": 0,
        "totalValueGained": 0
      },
      {
        "rosterId": 7,
        "teamName": "Breece Lightning",
        "realName": "Johnny",
        "sleeperUsername": "jwalters74",
        "nickname": "Johnny",
        "tradeCount": 0,
        "winRate": 0,
        "avgMargin": 0,
        "totalValueGained": 0
      },
      {
        "rosterId": 8,
        "teamName": "TRIPS",
        "realName": "Tyler",
        "sleeperUsername": "tylerpilgrim",
        "nickname": "Tyler",
        "tradeCount": 0,
        "winRate": 0,
        "avgMargin": 0,
        "totalValueGained": 0
      },
      {
        "rosterId": 9,
        "teamName": "Gaeta Spur FC",
        "realName": "Matt",
        "sleeperUsername": "mgaeta23",
        "nickname": "Gaeta",
        "tradeCount": 0,
        "winRate": 0,
        "avgMargin": 0,
        "totalValueGained": 0
      },
      {
        "rosterId": 10,
        "teamName": "Rashid Shaheed Truthers",
        "realName": "Jake",
        "sleeperUsername": "jakeduf",
        "nickname": "Jake",
        "tradeCount": 0,
        "winRate": 0,
        "avgMargin": 0,
        "totalValueGained": 0
      },
      {
        "rosterId": 11,
        "teamName": "Good Will Hunting",
        "realName": "Will",
        "sleeperUsername": "wkerwin",
        "nickname": "Will",
        "tradeCount": 0,
        "winRate": 0,
        "avgMargin": 0,
        "totalValueGained": 0
      },
      {
        "rosterId": 12,
        "teamName": "The Life of Showtime",
        "realName": "Don",
        "sleeperUsername": "donewton",
        "nickname": "Don",
        "tradeCount": 0,
        "winRate": 0,
        "avgMargin": 0,
        "totalValueGained": 0
      }
    ],
    "summary": {
      "totalTeams": 12,
      "totalTrades": 70
    }
  }
}